{
    "team": [
        {
            "name": "Paarkavi Jeyatheeswaran",
            "email": "e21206@eng.pdn.ac.lk",
            "eNumber": "E/21/206"
        },
        {
            "name": "Pavindran Velalagan",
            "email": "e21283@eng.pdn.ac.lk",
            "eNumber": "E/21/283"
        },
        {
            "name": "Shagiththiah Kirupakaran",
            "email": "e21375@eng.pdn.ac.lk",
            "eNumber": "E/21/375"
        },
        {
            "name": "Suthail A.L.M.",
            "email": "e21395@eng.pdn.ac.lk",
            "eNumber": "E/21/395"
        }
    ],
    "supervisors": [
        {
            "name": "Ms. Yasodha Vimukthi",
            "email": "yasodhav@eng.pdn.ac.lk"
        },
        {
            "name": "Dr. Isuru Nawinne",
            "email": "isurunawinne@eng.pdn.ac.lk"
        }
    ],
    "tags": ["Web", "Embedded Systems"]
}
